LICENSE
MANIFEST.in
README.rst
requirements.txt
setup.cfg
setup.py
ckanext/__init__.py
ckanext/papaya/__init__.py
ckanext/papaya/plugin.py
ckanext/papaya/fanstatic/papaya.css
ckanext/papaya/fanstatic/papaya.js
ckanext/papaya/templates/papaya_form.html
ckanext/papaya/templates/papaya_view.html
ckanext/papaya/tests/__init__.py
ckanext/papaya/tests/test_plugin.py
ckanext_papaya.egg-info/PKG-INFO
ckanext_papaya.egg-info/SOURCES.txt
ckanext_papaya.egg-info/dependency_links.txt
ckanext_papaya.egg-info/entry_points.txt
ckanext_papaya.egg-info/namespace_packages.txt
ckanext_papaya.egg-info/top_level.txt